plofeld/__init__.py
plofeld/elements.py
plofeld/fields.py
plofeld-0.0.1.dist-info/LICENSE
plofeld-0.0.1.dist-info/METADATA
plofeld-0.0.1.dist-info/WHEEL
plofeld-0.0.1.dist-info/top_level.txt
plofeld-0.0.1.dist-info/RECORD
