Metadata-Version: 2.1
Name: plofeld
Version: 0.0.1
Summary: Plotting functions for physical fields.
Home-page: https://github.com/JoschD/plofeld
Author: JoschD
Author-email: JoschD@github.com
License: MIT
Platform: UNKNOWN
Classifier: Development Status :: 5 - Production/Stable
Classifier: Intended Audience :: Science/Research
Classifier: License :: OSI Approved :: MIT License
Classifier: Natural Language :: English
Classifier: Operating System :: OS Independent
Classifier: Programming Language :: Python :: 3 :: Only
Classifier: Programming Language :: Python :: 3.7
Classifier: Programming Language :: Python :: 3.8
Classifier: Programming Language :: Python :: 3.9
Classifier: Topic :: Scientific/Engineering
Classifier: Topic :: Software Development :: Libraries :: Python Modules
Classifier: Typing :: Typed
Requires-Python: >=3.7
License-File: LICENSE
Requires-Dist: numpy (>=1.19.0)
Requires-Dist: scipy (>=1.7.0)
Requires-Dist: pandas (>=1.3)
Requires-Dist: matplotlib (>=3.4.0)
Provides-Extra: all
Requires-Dist: pytest (>=5.2) ; extra == 'all'
Requires-Dist: pytest-cov (>=2.9) ; extra == 'all'
Requires-Dist: sphinx ; extra == 'all'
Requires-Dist: sphinx-rtd-theme ; extra == 'all'
Provides-Extra: doc
Requires-Dist: sphinx ; extra == 'doc'
Requires-Dist: sphinx-rtd-theme ; extra == 'doc'
Provides-Extra: test
Requires-Dist: pytest (>=5.2) ; extra == 'test'
Requires-Dist: pytest-cov (>=2.9) ; extra == 'test'
